Metadata-Version: 2.1
Name: layerai
Version: 0.0.1
Summary: The Layer SDK
Home-page: https://layer.ai
Author: Layer
Author-email: python-sdk@layer.ai
License: UNKNOWN
Platform: UNKNOWN
Classifier: Programming Language :: Python :: 3
Classifier: License :: OSI Approved :: Apache Software License
Classifier: Operating System :: OS Independent
Requires-Python: >=3.7
